wombo/__init__.py
wombo/api/__init__.py
wombo/api/dream.py
wombo/base/__init__.py
wombo/base/dream.py
wombo/cli/__init__.py
wombo/cli/app.py
wombo/cli/login.py
wombo/cli/status.py
wombo/cli/styles.py
wombo/cli/task.py
wombo/models/__init__.py
wombo/models/style.py
wombo/models/task.py
wombo-0.7.0.dist-info/METADATA
wombo-0.7.0.dist-info/WHEEL
wombo-0.7.0.dist-info/entry_points.txt
wombo-0.7.0.dist-info/licenses/LICENSE
wombo-0.7.0.dist-info/RECORD
