Metadata-Version: 2.4
Name: wombo
Version: 0.7.0
Summary: Image generation module. I use the dream neural network from wombo for my work.
Project-URL: Homepage, https://github.com/pokedim13/wombo
Project-URL: Documentation, https://github.com/pokedim13/wombo
Project-URL: Repository, https://github.com/pokedim13/wombo.git
Project-URL: Issues, https://github.com/pokedim13/wombo/issues
Author-email: Aleksey Baev <skinxedovich@vk.com>
Maintainer-email: Aleksey Baev <skinxedovich@vk.com>
License: MIT License
License-File: LICENSE
Keywords: API,SDK,dream,wombo
Requires-Python: >=3.12
Requires-Dist: httpx>=0.28.1
Requires-Dist: pydantic>=2.10.6
Provides-Extra: cli
Requires-Dist: rich>=13.7.1; extra == 'cli'
Requires-Dist: typer>=0.9.0; extra == 'cli'
